langchain_support/__init__.py
langchain_support/graph.py
langchain_support-0.1.0.dist-info/METADATA
langchain_support-0.1.0.dist-info/WHEEL
langchain_support-0.1.0.dist-info/top_level.txt
langchain_support-0.1.0.dist-info/RECORD
