Metadata-Version: 2.4
Name: langchain-support
Version: 0.1.0
Summary: Utility package for LangChain support
Requires-Python: >=3.11
Requires-Dist: langchain-core>=0.3.76
Requires-Dist: langgraph>=0.6.7
